LICENSE
MANIFEST.in
README.md
mico-cube.reg
post-script.py
pypi_readme.rst
setup.py
mico/__init__.py
mico/mico.py
mico_cube.egg-info/PKG-INFO
mico_cube.egg-info/SOURCES.txt
mico_cube.egg-info/dependency_links.txt
mico_cube.egg-info/entry_points.txt
mico_cube.egg-info/top_level.txt