Metadata-Version: 1.0
Name: mico-cube
Version: 1.0.17
Summary: MXCHIP MiCO command line tool for repositories version control, publishing and updating code from remotely hosted repositories, and invoking MiCO OS own build system and export functions, among other operations
Home-page: https://code.aliyun.com/mico/mico-cube
Author: MXCHIP MiCO
Author-email: yangsw@mxchip.com
License: Apache License
